[
{
    "model": "contacts.contact",
    "pk": 1,
    "fields": {
        "first_name": "Farel",
        "last_name": "Malhomme",
        "car_id": 1,
        "customer_need": "I'd like to know your best price for this",
        "car_title": "2017 Ferrari 488 GTB",
        "city": "Austin",
        "state": "g hgh",
        "email": "dorianlenoumi@gmail.com",
        "phone": "98175000",
        "message": "Combien coûte cette voiture ?",
        "user_id": 0,
        "create_date": "2023-01-30T15:51:18.199Z"
    }
},
{
    "model": "contacts.contact",
    "pk": 2,
    "fields": {
        "first_name": "Damein",
        "last_name": "dals",
        "car_id": 4,
        "customer_need": "I'm interested in this",
        "car_title": "2017 Jaguar F-PACE",
        "city": "Austin",
        "state": "g hgh",
        "email": "dorianlenoumi@gmail.com",
        "phone": "98175000",
        "message": "sdfsdsd",
        "user_id": 2,
        "create_date": "2023-01-30T16:03:01.984Z"
    }
},
{
    "model": "contacts.contact",
    "pk": 3,
    "fields": {
        "first_name": "Damein",
        "last_name": "dals",
        "car_id": 2,
        "customer_need": "I'm interested in this",
        "car_title": "2017 Ford Edge",
        "city": "Cotonou",
        "state": "g hgh",
        "email": "dorianlenoumi@gmail.com",
        "phone": "45235352",
        "message": "dfvdfvsdf",
        "user_id": 2,
        "create_date": "2023-01-30T16:21:05.652Z"
    }
},
{
    "model": "contacts.contact",
    "pk": 4,
    "fields": {
        "first_name": "Damein",
        "last_name": "dals",
        "car_id": 3,
        "customer_need": "I'm interested in this",
        "car_title": "2017 Ford F-250 Super Duty",
        "city": "Cotonou",
        "state": "g hgh",
        "email": "dorianlenoumi@gmail.com",
        "phone": "98175000",
        "message": "vsdfvsf",
        "user_id": 2,
        "create_date": "2023-01-30T16:23:14.057Z"
    }
},
{
    "model": "contacts.contact",
    "pk": 5,
    "fields": {
        "first_name": "Damein",
        "last_name": "dals",
        "car_id": 5,
        "customer_need": "I'm interested in this",
        "car_title": "2018 Toyota 4Runner",
        "city": "Cotonou",
        "state": "g hgh",
        "email": "dorianlenoumi@gmail.com",
        "phone": "98175000",
        "message": "dfvdfcvdcvdd",
        "user_id": 2,
        "create_date": "2023-01-30T16:41:24.678Z"
    }
},
{
    "model": "contacts.contact",
    "pk": 6,
    "fields": {
        "first_name": "Damein",
        "last_name": "dals",
        "car_id": 5,
        "customer_need": "I'm interested in this",
        "car_title": "2018 Toyota 4Runner",
        "city": "Cotonou",
        "state": "g hgh",
        "email": "dorianlenoumi@gmail.com",
        "phone": "98175000",
        "message": "dfvdfcvdcvdd",
        "user_id": 2,
        "create_date": "2023-01-30T16:41:27.729Z"
    }
},
{
    "model": "cars.car",
    "pk": 1,
    "fields": {
        "car_title": "2017 Ferrari 488 GTB",
        "state": "TX",
        "city": "Austin",
        "color": "White",
        "model": "488 GTB",
        "year": 2017,
        "condition": "Used",
        "price": 40000,
        "description": "<p>The&nbsp;<strong>Ferrari 488</strong>&nbsp;(Type F142M) is a&nbsp;<a href=\"https://en.wikipedia.org/wiki/Rear_mid-engine,_rear-wheel_drive_layout\" title=\"Rear mid-engine, rear-wheel drive layout\">mid-engine</a>&nbsp;<a href=\"https://en.wikipedia.org/wiki/Sports_car\" title=\"Sports car\">sports car</a>&nbsp;produced by the Italian automobile manufacturer&nbsp;<a href=\"https://en.wikipedia.org/wiki/Ferrari\" title=\"Ferrari\">Ferrari</a>. The car replaced the&nbsp;<a href=\"https://en.wikipedia.org/wiki/Ferrari_458\" title=\"Ferrari 458\">458</a>, being the first mid-engine Ferrari to use a turbocharged V8 since the&nbsp;<a href=\"https://en.wikipedia.org/wiki/Ferrari_F40\" title=\"Ferrari F40\">F40</a>. It was succeeded by the&nbsp;<a href=\"https://en.wikipedia.org/wiki/Ferrari_F8\" title=\"Ferrari F8\">Ferrari F8</a>.</p>\r\n\r\n<p>The car is powered by a 3.9-litre&nbsp;<a href=\"https://en.wikipedia.org/wiki/Twin-turbocharged\" title=\"Twin-turbocharged\">twin-turbocharged</a>&nbsp;<a href=\"https://en.wikipedia.org/wiki/V8_engine\" title=\"V8 engine\">V8 engine</a>, smaller in displacement but generating a higher power output than the 458&#39;s&nbsp;<a href=\"https://en.wikipedia.org/wiki/Naturally_aspirated_engine\" title=\"Naturally aspirated engine\">naturally aspirated engine</a>. The 488 GTB was named &quot;The Supercar of the Year 2015&quot; by car magazine&nbsp;<em><a href=\"https://en.wikipedia.org/wiki/Top_Gear_(magazine)\" title=\"Top Gear (magazine)\">Top Gear</a></em>, as well as becoming&nbsp;<em><a href=\"https://en.wikipedia.org/wiki/Motor_Trend\" title=\"Motor Trend\">Motor Trend</a></em>&#39;s 2017 &quot;Best Driver&#39;s Car&quot;.<a href=\"https://en.wikipedia.org/wiki/Ferrari_488#cite_note-7\">[7]</a>&nbsp;<a href=\"https://en.wikipedia.org/wiki/Jeremy_Clarkson\" title=\"Jeremy Clarkson\">Jeremy Clarkson</a>&nbsp;announced the 488 Pista as his 2019 Supercar of the Year.<a href=\"https://en.wikipedia.org/wiki/Ferrari_488#cite_note-8\">[8]</a>&nbsp;The 488 was succeeded by the&nbsp;<a href=\"https://en.wikipedia.org/wiki/Ferrari_F8\" title=\"Ferrari F8\">F8 Tributo</a>&nbsp;in February 2019.</p>",
        "car_photo": "photos/2023/01/27/1902536891.jpg",
        "car_photo_1": "photos/2023/01/27/1902536917.jpg",
        "car_photo_2": "photos/2023/01/27/1902537043.jpg",
        "car_photo_3": "photos/2023/01/27/1902537077.jpg",
        "car_photo_4": "photos/2023/01/27/1902537082.jpg",
        "features": "Cruise Control,Audio Interface,Airbags,ParkAssist,Power Steering,Reversing Camera",
        "body_style": "Sport",
        "engine": "3.4L Mld-Engine V6",
        "transmission": "Automatic",
        "interior": "Grey",
        "miles": 10000,
        "doors": "3",
        "passengers": 5,
        "vin_no": "98UUWPLONEUJENJ E",
        "milage": 5,
        "fuel_type": "Petrol",
        "no_of_owners": "1",
        "is_featured": true,
        "created_date": "2023-01-27T08:20:31Z"
    }
},
{
    "model": "cars.car",
    "pk": 2,
    "fields": {
        "car_title": "2017 Ford Edge",
        "state": "TX",
        "city": "Dallas",
        "color": "Black",
        "model": "Edge",
        "year": 2017,
        "condition": "Used",
        "price": 25000,
        "description": "<p>Le SE comprend des si&egrave;ges en tissu, climatisation manuelle monozone, cha&icirc;ne st&eacute;r&eacute;o AM/FM avec lecteur CD monodisque/MP3 et jantes de 17 pouces en aluminium peint.</p>\r\n\r\n<p>Le SEL comprend des si&egrave;ges en tissu uniques, si&egrave;ge conducteur &agrave; six r&eacute;glages &eacute;lectriques, cha&icirc;ne st&eacute;r&eacute;o AM/FM haut de gamme avec lecteur CD &agrave; six disques/MP3 sur le tableau de bord, volant gain&eacute; de cuir avec commandes audio secondaires et jantes de 18 pouces en aluminium peint.</p>\r\n\r\n<p>Le SEL Plus, connu plus tard sous le nom de Limited, comprend des si&egrave;ges garnis de cuir, et &eacute;ventuellement, si&egrave;ge du passager avant rabattable &agrave; plat et &agrave; r&eacute;glage &eacute;lectrique, d&eacute;verrouillage du dossier des si&egrave;ges de deuxi&egrave;me rang&eacute;e EasyFold, contr&ocirc;le &eacute;lectronique et automatique de la temp&eacute;rature bi-zones, syst&egrave;me de connectivit&eacute; embarqu&eacute; SYNC et jantes haut de gamme de 18 pouces en aluminium chrom&eacute;. Le niveau de finition Limited a remplac&eacute; le SEL Plus en 2008.</p>\r\n\r\n<p>Le niveau de finition Sport a fait ses d&eacute;buts au Salon de l&#39;auto de Chicago 2008, avec des ventes commen&ccedil;ant en tant que mod&egrave;le de 2009<a href=\"https://fr.wikipedia.org/wiki/Ford_Edge#cite_note-1\">1</a>. Le niveau de finition comprend des garnitures en cuir avec des inserts en faux su&egrave;de gris, si&egrave;ges inclinables en 60/40 et rabattables &agrave; plat avec accoudoir central rabattable, d&eacute;verrouillage du dossier des si&egrave;ges de deuxi&egrave;me rang&eacute;e (commercialis&eacute; sous le nom d&#39;EasyFold), cha&icirc;ne st&eacute;r&eacute;o AM/FM haut de gamme avec lecteur CD &agrave; six disques/MP3 sur le tableau de bord, syst&egrave;me de connectivit&eacute; embarqu&eacute; SYNC, embouts d&#39;&eacute;chappement de grand diam&egrave;tre chrom&eacute;s, jantes haut de gamme de 20 pouces en aluminium chrom&eacute;, toutes les garnitures de la m&ecirc;me couleur que la carrosserie et roues de 22 pouces en option.</p>",
        "car_photo": "photos/2023/01/28/1901478607.jpg",
        "car_photo_1": "photos/2023/01/28/1901478618.jpg",
        "car_photo_2": "photos/2023/01/28/1901478646.jpg",
        "car_photo_3": "photos/2023/01/28/1901478672.jpg",
        "car_photo_4": "photos/2023/01/28/1901478687.jpg",
        "features": "Cruise Control,Audio Interface,Airbags,Air Conditioning,Power Steering,Reversing Camera,Auto Start/Stop,Wind Deflector,Bluetooth Handset",
        "body_style": "SUV",
        "engine": "3.4L Mld-Engine V7",
        "transmission": "Automatic",
        "interior": "Grey",
        "miles": 1500,
        "doors": "5",
        "passengers": 5,
        "vin_no": "98UUWPLONEUJENJ E",
        "milage": 8,
        "fuel_type": "Petrol",
        "no_of_owners": "2",
        "is_featured": true,
        "created_date": "2023-01-28T08:20:38Z"
    }
},
{
    "model": "cars.car",
    "pk": 3,
    "fields": {
        "car_title": "2017 Ford F-250 Super Duty",
        "state": "NY",
        "city": "Ohio",
        "color": "Black",
        "model": "F-250",
        "year": 2017,
        "condition": "Used",
        "price": 30000,
        "description": "<p>Le&nbsp;<strong>Ford Super Duty</strong>&nbsp;(abr&eacute;viation de F-Series Super Duty) est une s&eacute;rie de&nbsp;<a href=\"https://fr.wikipedia.org/wiki/Pick-up\" title=\"Pick-up\">pick-ups</a>&nbsp;fabriqu&eacute;s par la&nbsp;<a href=\"https://fr.wikipedia.org/wiki/Ford_Motor_Company\" title=\"Ford Motor Company\">Ford Motor Company</a>. Introduits en 1998 pour l&#39;ann&eacute;e mod&egrave;le 1999 (l&#39;ann&eacute;e mod&egrave;le 1998 a &eacute;t&eacute; ignor&eacute;e), les pickups F-Series Super Duty ont marqu&eacute; l&#39;ajout d&#39;un pick-up robuste &agrave; la gamme&nbsp;<a href=\"https://fr.wikipedia.org/wiki/Ford_F-Series\" title=\"Ford F-Series\">Ford F-Series</a>&nbsp;avec des nouvelles versions du F-250, des pickups F-350 et F-450, tandis que les pr&eacute;c&eacute;dents ch&acirc;ssis-cabines F-Super Duty de 1987 &agrave; 1997 ont &eacute;t&eacute; remplac&eacute;s par les ch&acirc;ssis-cabines F-450 et F-550 Super Duty.</p>\r\n\r\n<p>Les pickups Super Duty utilisent un ch&acirc;ssis distinct du&nbsp;<a href=\"https://fr.wikipedia.org/wiki/Ford_F-150\" title=\"Ford F-150\">Ford F-150</a>&nbsp;plus l&eacute;ger, avec des composants de ch&acirc;ssis et de suspension plus lourds pour permettre une charge utile et des capacit&eacute;s de remorquage plus &eacute;lev&eacute;es; en outre, la gamme de produits a continu&eacute; &agrave; utiliser les moteurs Diesel PowerStroke de Ford. Avec un poids nominal brut du v&eacute;hicule sup&eacute;rieur &agrave; 3&nbsp;900&nbsp;kg, les pickups Super Duty sont des pickups de cat&eacute;gorie 2 et 3, tandis que les pickups ch&acirc;ssis-cabine sont de cat&eacute;gorie 4 et de cat&eacute;gorie 5. Le ch&acirc;ssis du F-Series Super Duty a &eacute;t&eacute; utilis&eacute; comme ch&acirc;ssis de base pour le SUV full-size&nbsp;<a href=\"https://fr.wikipedia.org/wiki/Ford_Excursion\" title=\"Ford Excursion\">Ford Excursion</a>.</p>",
        "car_photo": "photos/2023/01/28/1894300894.jpg",
        "car_photo_1": "photos/2023/01/28/1894300905.jpg",
        "car_photo_2": "photos/2023/01/28/1894300920.jpg",
        "car_photo_3": "photos/2023/01/28/1900155012.jpg",
        "car_photo_4": "photos/2023/01/28/1900155133.jpg",
        "features": "Cruise Control,Audio Interface,Airbags,Seat Heating,Alarm System,Power Steering,Direct Fuel Injection,Auto Start/Stop,Bluetooth Handset",
        "body_style": "SUV",
        "engine": "3.4L Mld-Engine V7",
        "transmission": "Automatic",
        "interior": "Grey",
        "miles": 13000,
        "doors": "2",
        "passengers": 2,
        "vin_no": "98UUWPLONEUJENJ77877",
        "milage": 10,
        "fuel_type": "Diesel",
        "no_of_owners": "1",
        "is_featured": false,
        "created_date": "2023-01-28T08:25:43Z"
    }
},
{
    "model": "cars.car",
    "pk": 4,
    "fields": {
        "car_title": "2017 Jaguar F-PACE",
        "state": "TX",
        "city": "Austin",
        "color": "Green",
        "model": "F-PACE",
        "year": 2017,
        "condition": "Used",
        "price": 50000,
        "description": "<p>La&nbsp;<strong>F-Pace</strong>&nbsp;est un&nbsp;<a href=\"https://fr.wikipedia.org/wiki/Sport_Utility_Vehicle\" title=\"Sport Utility Vehicle\">SUV</a>&nbsp;commercialis&eacute; &agrave; partir de&nbsp;<a href=\"https://fr.wikipedia.org/wiki/2015\" title=\"2015\">2015</a>&nbsp;par le&nbsp;<a href=\"https://fr.wikipedia.org/wiki/Constructeur_automobile\" title=\"Constructeur automobile\">constructeur automobile</a>&nbsp;<a href=\"https://fr.wikipedia.org/wiki/Royaume-Uni\" title=\"Royaume-Uni\">britannique</a>&nbsp;<a href=\"https://fr.wikipedia.org/wiki/Jaguar_(automobile)\" title=\"Jaguar (automobile)\">Jaguar</a>. Il s&#39;agit du premier SUV de la marque. Elle est &eacute;lue &laquo;&nbsp;World Car of the Year&nbsp;2017&nbsp;&raquo; (<a href=\"https://fr.wikipedia.org/wiki/Voiture_mondiale_de_l%27ann%C3%A9e\" title=\"Voiture mondiale de l'année\">Voiture mondiale de l&#39;ann&eacute;e</a>&nbsp;2017) &agrave; l&#39;occasion du&nbsp;<a href=\"https://fr.wikipedia.org/wiki/Salon_de_l%27automobile_de_New_York\" title=\"Salon de l'automobile de New York\">salon de New York</a>&nbsp;en&nbsp;mars 2017<a href=\"https://fr.wikipedia.org/wiki/Jaguar_F-Pace#cite_note-1\">1</a></p>\r\n\r\n<p>a F-Pace est pr&eacute;sent&eacute;e en&nbsp;septembre 2015&nbsp;au&nbsp;<a href=\"https://fr.wikipedia.org/wiki/Salon_de_l%27automobile_de_Francfort\" title=\"Salon de l'automobile de Francfort\">salon de l&#39;automobile de Francfort</a><a href=\"https://fr.wikipedia.org/wiki/Jaguar_F-Pace#cite_note-2\">2</a>. La veille de l&#39;ouverture du salon au public, le&nbsp;17 septembre 2015, un record du monde est r&eacute;alis&eacute; avec le passage d&#39;un looping de 19&nbsp;m&nbsp;de diam&egrave;tre avec le SUV, le cascadeur Terry Grant &eacute;tant &agrave; son bord<a href=\"https://fr.wikipedia.org/wiki/Jaguar_F-Pace#cite_note-3\">3</a>,<a href=\"https://fr.wikipedia.org/wiki/Jaguar_F-Pace#cite_note-4\">4</a>.</p>\r\n\r\n<p>Elle est assembl&eacute;e &agrave;&nbsp;<a href=\"https://fr.wikipedia.org/wiki/Solihull\" title=\"Solihull\">Solihull</a>&nbsp;en&nbsp;<a href=\"https://fr.wikipedia.org/wiki/Angleterre\" title=\"Angleterre\">Angleterre</a>&nbsp;et repose sur la plate-forme de la&nbsp;<a href=\"https://fr.wikipedia.org/wiki/Jaguar_XE\" title=\"Jaguar XE\">Jaguar XE</a>.</p>\r\n\r\n<ul>\r\n</ul>",
        "car_photo": "photos/2023/01/28/1902932503.jpg",
        "car_photo_1": "photos/2023/01/28/1902932514.jpg",
        "car_photo_2": "photos/2023/01/28/1902932528.jpg",
        "car_photo_3": "photos/2023/01/28/1902932542.jpg",
        "car_photo_4": "",
        "features": "Cruise Control,Audio Interface,Airbags,Alarm System,ParkAssist,Direct Fuel Injection,Auto Start/Stop,Bluetooth Handset",
        "body_style": "SUV",
        "engine": "3.4L Mld-Engine V4",
        "transmission": "Automatic",
        "interior": "Black",
        "miles": 12500,
        "doors": "5",
        "passengers": 5,
        "vin_no": "98UUWPLONEUJENJY8233",
        "milage": 7,
        "fuel_type": "Petrol",
        "no_of_owners": "1",
        "is_featured": true,
        "created_date": "2023-01-28T08:29:16Z"
    }
},
{
    "model": "cars.car",
    "pk": 5,
    "fields": {
        "car_title": "2018 Toyota 4Runner",
        "state": "CO",
        "city": "Mihouwi",
        "color": "Grey",
        "model": "X-RAY",
        "year": 2018,
        "condition": "Used",
        "price": 77009,
        "description": "<p>The&nbsp;<strong>Toyota 4Runner</strong>&nbsp;is an&nbsp;<a href=\"https://en.wikipedia.org/wiki/SUV\" title=\"SUV\">SUV</a>&nbsp;manufactured by the Japanese automaker&nbsp;<a href=\"https://en.wikipedia.org/wiki/Toyota\" title=\"Toyota\">Toyota</a>&nbsp;and marketed globally since 1984, across five generations. In Japan, it was marketed as the&nbsp;<strong>Toyota Hilux Surf</strong>&nbsp;(<a href=\"https://en.wikipedia.org/wiki/Japanese_language\" title=\"Japanese language\">Japanese</a>:&nbsp;トヨタ・ハイラックスサーフ,&nbsp;<a href=\"https://en.wikipedia.org/wiki/Hepburn_romanization\" title=\"Hepburn romanization\">Hepburn</a>:&nbsp;<em>Toyota Hairakkususāfu</em>)&nbsp;and was withdrawn from the market in 2009. The original 4Runner was a&nbsp;<a href=\"https://en.wikipedia.org/wiki/Compact_SUV\" title=\"Compact SUV\">compact SUV</a>&nbsp;and little more than a Toyota&nbsp;<a href=\"https://en.wikipedia.org/wiki/Toyota_Hilux\" title=\"Toyota Hilux\">Hilux</a>&nbsp;pickup truck with a fiberglass shell over the bed, but the model has since undergone significant independent development into a cross between a compact and a mid-size SUV. All 4Runners have been built in Japan at Toyota&#39;s&nbsp;<a href=\"https://en.wikipedia.org/wiki/Tahara_plant\" title=\"Tahara plant\">plant</a>&nbsp;in&nbsp;<a href=\"https://en.wikipedia.org/wiki/Tahara,_Aichi\" title=\"Tahara, Aichi\">Tahara, Aichi</a>, or at the&nbsp;<a href=\"https://en.wikipedia.org/wiki/Hino_Motors\" title=\"Hino Motors\">Hino Motors</a>&nbsp;(a Toyota subsidiary) plant in&nbsp;<a href=\"https://en.wikipedia.org/wiki/Hamura\" title=\"Hamura\">Hamura</a>.</p>\r\n\r\n<p>The name &quot;4Runner&quot; was created by copywriter Robert Nathan with the&nbsp;<a href=\"https://en.wikipedia.org/wiki/Saatchi_%26_Saatchi\" title=\"Saatchi &amp; Saatchi\">Saatchi &amp; Saatchi</a>&nbsp;advertising company as a play on the term &quot;forerunner&quot;. The agency held contests to invent new names for Toyota&#39;s forthcoming vehicles. According to Toyota, the &quot;4&quot; described the vehicle&#39;s 4-wheel drive system while &quot;Runner&quot; was a reference to its all-terrain capabilities and how it could &quot;run&quot; off road.<a href=\"https://en.wikipedia.org/wiki/Toyota_4Runner#cite_note-1\">[1]</a></p>\r\n\r\n<p>For some markets, the Hilux Surf was replaced in 2005 by the similar&nbsp;<a href=\"https://en.wikipedia.org/wiki/Toyota_Fortuner\" title=\"Toyota Fortuner\">Fortuner</a>, which is based on the&nbsp;<a href=\"https://en.wikipedia.org/wiki/Toyota_Hilux\" title=\"Toyota Hilux\">Hilux</a>&nbsp;platform.</p>\r\n\r\n<p>As of 2021, the 4Runner is marketed in the Bahamas, Bolivia, Canada, Chile, Colombia, Costa Rica, El Salvador, Guatemala, Panama, Peru, the United States and Venezuela.</p>\r\n\r\n<p>The 4Runner came in at number five in a 2019 study by&nbsp;<a href=\"https://en.wikipedia.org/wiki/ISeeCars.com\" title=\"ISeeCars.com\">iSeeCars.com</a>&nbsp;ranking the longest-lasting vehicles in the US. The 4Runner had 3.9&nbsp;percent of vehicles over 200,000 miles (320,000&nbsp;km), according to the study.<a href=\"https://en.wikipedia.org/wiki/Toyota_4Runner#cite_note-2\">[2]</a></p>",
        "car_photo": "photos/2023/01/28/1893633875.jpg",
        "car_photo_1": "photos/2023/01/28/1893633879.jpg",
        "car_photo_2": "photos/2023/01/28/1893633884.jpg",
        "car_photo_3": "photos/2023/01/28/1896836883.jpg",
        "car_photo_4": "photos/2023/01/28/1896836887.jpg",
        "features": "Cruise Control,Audio Interface,Airbags,Seat Heating,Alarm System,Power Steering,Reversing Camera,Wind Deflector",
        "body_style": "SUV",
        "engine": "3.4L Mld-Engine V7",
        "transmission": "Automatic",
        "interior": "Black",
        "miles": 100,
        "doors": "6",
        "passengers": 6,
        "vin_no": "98UUWPLONEUJEN8999",
        "milage": 23,
        "fuel_type": "Petrol",
        "no_of_owners": "2",
        "is_featured": true,
        "created_date": "2023-01-28T08:32:32Z"
    }
},
{
    "model": "cars.car",
    "pk": 6,
    "fields": {
        "car_title": "2018 Toyota Corolla",
        "state": "ID",
        "city": "Liase",
        "color": "White",
        "model": "SEV-IU",
        "year": 2018,
        "condition": "Used",
        "price": 12000,
        "description": "<p>The&nbsp;<strong>Toyota Corolla</strong>&nbsp;(<a href=\"https://en.wikipedia.org/wiki/Japanese_language\" title=\"Japanese language\">Japanese</a>:&nbsp;トヨタ・カローラ,&nbsp;<a href=\"https://en.wikipedia.org/wiki/Hepburn_romanization\" title=\"Hepburn romanization\">Hepburn</a>:&nbsp;<em>Toyota Karōra</em>)&nbsp;is a series of&nbsp;<a href=\"https://en.wikipedia.org/wiki/Compact_car\" title=\"Compact car\">compact cars</a>&nbsp;(formerly&nbsp;<a href=\"https://en.wikipedia.org/wiki/Subcompact_car\" title=\"Subcompact car\">subcompact</a>) manufactured and marketed globally by the Japanese automaker&nbsp;<a href=\"https://en.wikipedia.org/wiki/Toyota_Motor_Corporation\" title=\"Toyota Motor Corporation\">Toyota Motor Corporation</a>. Introduced in 1966, the Corolla was the best-selling car worldwide by 1974 and has been one of the best-selling cars in the world since then. In 1997, the Corolla became the&nbsp;<a href=\"https://en.wikipedia.org/wiki/List_of_best-selling_automobiles\" title=\"List of best-selling automobiles\">best-selling nameplate in the world</a>, surpassing the&nbsp;<a href=\"https://en.wikipedia.org/wiki/Volkswagen_Beetle\" title=\"Volkswagen Beetle\">Volkswagen Beetle</a>.<a href=\"https://en.wikipedia.org/wiki/Toyota_Corolla#cite_note-1\">[1]</a>&nbsp;Toyota reached the milestone of 50 million Corollas sold over twelve generations in 2021.<a href=\"https://en.wikipedia.org/wiki/Toyota_Corolla#cite_note-50million-2\">[2]</a></p>\r\n\r\n<p>The name&nbsp;<em><a href=\"https://en.wikipedia.org/wiki/Corolla_(headgear)\" title=\"Corolla (headgear)\">Corolla</a></em>&nbsp;is part of Toyota&#39;s naming tradition of using names derived from the&nbsp;<a href=\"https://en.wikipedia.org/wiki/Toyota_Crown\" title=\"Toyota Crown\">Toyota Crown</a>&nbsp;for sedans, with&nbsp;<em>&quot;<a href=\"https://en.wiktionary.org/wiki/corolla\" title=\"wikt:corolla\">corolla</a>&quot;</em>&nbsp;<a href=\"https://en.wikipedia.org/wiki/Latin\" title=\"Latin\">Latin</a>&nbsp;for &quot;small crown&quot;.<a href=\"https://en.wikipedia.org/wiki/Toyota_Corolla#cite_note-3\">[3]</a>&nbsp;The Corolla has always been exclusive in Japan to&nbsp;<em><a href=\"https://en.wikipedia.org/wiki/Toyota_Corolla_Store\" title=\"Toyota Corolla Store\">Toyota Corolla Store</a></em>&nbsp;locations, and manufactured in Japan with a twin, called the&nbsp;<a href=\"https://en.wikipedia.org/wiki/Toyota_Sprinter\" title=\"Toyota Sprinter\">Toyota Sprinter</a>&nbsp;until 2000. From 2006 to 2018 in Japan and much of the world, and from 2018 to 2020 in Taiwan, the hatchback companion had been called the&nbsp;<a href=\"https://en.wikipedia.org/wiki/Toyota_Auris\" title=\"Toyota Auris\">Toyota Auris</a>.</p>\r\n\r\n<p>Early models were mostly&nbsp;<a href=\"https://en.wikipedia.org/wiki/Rear-wheel_drive\" title=\"Rear-wheel drive\">rear-wheel drive</a>, while later models have been&nbsp;<a href=\"https://en.wikipedia.org/wiki/Front-wheel_drive\" title=\"Front-wheel drive\">front-wheel drive</a>.&nbsp;<a href=\"https://en.wikipedia.org/wiki/Four-wheel_drive\" title=\"Four-wheel drive\">Four-wheel drive</a>&nbsp;versions have also been produced, and it has undergone several major redesigns. The Corolla&#39;s traditional competitors have been the&nbsp;<a href=\"https://en.wikipedia.org/wiki/Nissan_Sunny\" title=\"Nissan Sunny\">Nissan Sunny</a>, introduced the same year as the Corolla in Japan and the later&nbsp;<a href=\"https://en.wikipedia.org/wiki/Nissan_Sentra\" title=\"Nissan Sentra\">Nissan Sentra</a>,&nbsp;<a href=\"https://en.wikipedia.org/wiki/Nissan_Sylphy\" title=\"Nissan Sylphy\">Nissan Sylphy</a>,&nbsp;<a href=\"https://en.wikipedia.org/wiki/Honda_Civic\" title=\"Honda Civic\">Honda Civic</a>&nbsp;and&nbsp;<a href=\"https://en.wikipedia.org/wiki/Mitsubishi_Lancer\" title=\"Mitsubishi Lancer\">Mitsubishi Lancer</a>. The Corolla&#39;s chassis designation code is &quot;E&quot;, as described in&nbsp;<a href=\"https://en.wikipedia.org/wiki/List_of_Toyota_model_codes\" title=\"List of Toyota model codes\">Toyota&#39;s chassis and engine codes.</a></p>",
        "car_photo": "photos/2023/01/28/1900893299.jpg",
        "car_photo_1": "photos/2023/01/28/1900893311.jpg",
        "car_photo_2": "photos/2023/01/28/1900893319.jpg",
        "car_photo_3": "photos/2023/01/28/1900893329.jpg",
        "car_photo_4": "photos/2023/01/28/1900893391.jpg",
        "features": "Cruise Control,Audio Interface,Seat Heating,Alarm System,Direct Fuel Injection,Auto Start/Stop,Wind Deflector",
        "body_style": "SILI",
        "engine": "3.4L Mld-Engine V4",
        "transmission": "Manuelle",
        "interior": "Black",
        "miles": 32,
        "doors": "4",
        "passengers": 4,
        "vin_no": "98UUWPLONEUJE9877",
        "milage": 2,
        "fuel_type": "Petrol",
        "no_of_owners": "3",
        "is_featured": false,
        "created_date": "2023-01-28T08:37:11Z"
    }
},
{
    "model": "pages.team",
    "pk": 2,
    "fields": {
        "first_name": "Michel",
        "last_name": "Nelson",
        "designation": "Web Developer",
        "photo": "photos/2023/01/27/avatar-10.jpg",
        "facebook_link": "http://www.facebook.com/farel",
        "twitter_link": "http://www.twitter.com/farel",
        "google_plus_link": "http://www.kits.com/farel",
        "created_date": "2023-01-27T15:59:12.681Z"
    }
},
{
    "model": "pages.team",
    "pk": 3,
    "fields": {
        "first_name": "Stone",
        "last_name": "Carolyn",
        "designation": "Creative Director",
        "photo": "photos/2023/01/27/avatar-11.jpg",
        "facebook_link": "http://www.facebook.com/farel",
        "twitter_link": "http://www.twitter.com/farel",
        "google_plus_link": "http://www.kits.com/farel",
        "created_date": "2023-01-27T15:59:57.660Z"
    }
},
{
    "model": "pages.team",
    "pk": 4,
    "fields": {
        "first_name": "Michelle",
        "last_name": "Nelson",
        "designation": "Support Manager",
        "photo": "photos/2023/01/27/avatar-9.jpg",
        "facebook_link": "http://www.facebook.com/farel",
        "twitter_link": "http://www.twitter.com/farel",
        "google_plus_link": "http://www.kits.com/farel",
        "created_date": "2023-01-27T16:00:35.990Z"
    }
},
{
    "model": "pages.team",
    "pk": 5,
    "fields": {
        "first_name": "Brandon",
        "last_name": "Miller",
        "designation": "Manager",
        "photo": "photos/2023/01/27/avatar-12_HUmELvr.jpg",
        "facebook_link": "http://www.facebook.com/farel",
        "twitter_link": "http://www.twitter.com/farel",
        "google_plus_link": "http://www.kits.com/farel",
        "created_date": "2023-01-27T16:01:01.825Z"
    }
},
{
    "model": "auth.user",
    "fields": {
        "password": "pbkdf2_sha256$260000$5B5cxFM1U2pg9vojW7DdBS$8a7HKTbU8nBdOxt12B1P/VLn2oaNBlrWEbYPyjTIn1A=",
        "last_login": "2023-01-30T15:51:46Z",
        "is_superuser": true,
        "username": "malhomme",
        "first_name": "Mal",
        "last_name": "Homme",
        "email": "farrellndv770@gmail.com",
        "is_staff": true,
        "is_active": true,
        "date_joined": "2023-01-27T15:10:39Z",
        "groups": [],
        "user_permissions": []
    }
},
{
    "model": "auth.user",
    "fields": {
        "password": "pbkdf2_sha256$260000$uxkhGhmezMEYt4VECx4KDV$ab2jqIA8jl/GL0vjQiDlTk9m9H78LEbeOFOLJiSQJGw=",
        "last_login": "2023-01-30T15:56:34.268Z",
        "is_superuser": false,
        "username": "admin",
        "first_name": "Damein",
        "last_name": "dals",
        "email": "dorianlenoumi@gmail.com",
        "is_staff": false,
        "is_active": true,
        "date_joined": "2023-01-30T12:53:17.327Z",
        "groups": [],
        "user_permissions": []
    }
},
{
    "model": "auth.user",
    "fields": {
        "password": "!1pxbgdgTVdDeKP7ulwH6eVFxER1GE2lDQ44oiVTS",
        "last_login": "2023-01-30T14:52:13.832Z",
        "is_superuser": false,
        "username": "dorian6",
        "first_name": "Dorian",
        "last_name": "Lenoumi",
        "email": "",
        "is_staff": false,
        "is_active": true,
        "date_joined": "2023-01-30T14:22:19.424Z",
        "groups": [],
        "user_permissions": []
    }
},
{
    "model": "auth.user",
    "fields": {
        "password": "!2PPP6p18rCpgscqzSyGZeBH3RWxTw5JrLdjftb1Z",
        "last_login": "2023-01-30T14:48:04.931Z",
        "is_superuser": false,
        "username": "malhomme0",
        "first_name": "Malhomme",
        "last_name": "Diffusion",
        "email": "",
        "is_staff": false,
        "is_active": true,
        "date_joined": "2023-01-30T14:48:04.308Z",
        "groups": [],
        "user_permissions": []
    }
},
{
    "model": "sessions.session",
    "pk": "1jucjdyiry45pwilni4nwjvp70ji117v",
    "fields": {
        "session_data": ".eJxVjEEOwiAQRe_C2hA6DCAu3fcMZAZQqgaS0q6MdzckXej2v_f-WwTatxL2ntewJHERIE6_G1N85jpAelC9Nxlb3daF5VDkQbucW8qv6-H-HRTqZdTWW8_W8FnhDbQio1FZbVSE7Bk9OeQpAwE6whi1dlElIELjlXN5Ep8vvzg3AA:1pMWWI:btkMQ5qdTbLmS_VmH9LZHUy1ra15jctuCLQbkwgUJ9U",
        "expire_date": "2023-02-13T15:56:34.379Z"
    }
},
{
    "model": "sessions.session",
    "pk": "fkxlf10qk072kac2qlfx6l9xpxcbikyx",
    "fields": {
        "session_data": ".eJxVjDEOwjAMRe-SGUV2SWjDyM4ZIseOSQGlUtNOiLtDpQ6w_vfef5lI61Li2vIcRzFng-bwuyXiR64bkDvV22R5qss8JrspdqfNXifJz8vu_h0UauVbu25APSVHoOB7BQpuwB6OnTgFxwI5BU1JJCij98jkg0fKKgxMIZj3B-B3OIQ:1pMWRf:XyCbvetmF0LxsSPKzSA0eIyFSx8mkOmPlFasfvzSYFU",
        "expire_date": "2023-02-13T15:51:47.087Z"
    }
},
{
    "model": "sites.site",
    "fields": {
        "domain": "localhost:8000",
        "name": "localhost:8000"
    }
},
{
    "model": "socialaccount.socialapp",
    "pk": 1,
    "fields": {
        "provider": "facebook",
        "name": "Facebook Login",
        "client_id": "719578343034053",
        "secret": "fe0bc04ea2817e4612a4e7e963ac4b27",
        "key": "",
        "sites": [
            [
                "localhost:8000"
            ]
        ]
    }
},
{
    "model": "socialaccount.socialapp",
    "pk": 2,
    "fields": {
        "provider": "google",
        "name": "Google Login",
        "client_id": "389480718372-eadg70rfik5ar40eppthu73qf8qkhh31.apps.googleusercontent.com",
        "secret": "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",
        "key": "",
        "sites": [
            [
                "localhost:8000"
            ]
        ]
    }
},
{
    "model": "socialaccount.socialaccount",
    "pk": 1,
    "fields": {
        "user": [
            "dorian6"
        ],
        "provider": "facebook",
        "uid": "1647659269011793",
        "last_login": "2023-01-30T14:52:13.381Z",
        "date_joined": "2023-01-30T14:22:19.708Z",
        "extra_data": "{\"id\": \"1647659269011793\", \"name\": \"Dorian Lenoumi\", \"first_name\": \"Dorian\", \"last_name\": \"Lenoumi\"}"
    }
},
{
    "model": "socialaccount.socialaccount",
    "pk": 2,
    "fields": {
        "user": [
            "malhomme0"
        ],
        "provider": "google",
        "uid": "102438143014238959121",
        "last_login": "2023-01-30T14:48:04.410Z",
        "date_joined": "2023-01-30T14:48:04.410Z",
        "extra_data": "{\"iss\": \"https://accounts.google.com\", \"azp\": \"389480718372-eadg70rfik5ar40eppthu73qf8qkhh31.apps.googleusercontent.com\", \"aud\": \"389480718372-eadg70rfik5ar40eppthu73qf8qkhh31.apps.googleusercontent.com\", \"sub\": \"102438143014238959121\", \"at_hash\": \"_OMpkxqLt00v5aN_VzBdzQ\", \"name\": \"Malhomme Diffusion\", \"picture\": \"https://lh3.googleusercontent.com/a/AEdFTp53tHk0kwANEoUM9dlE4OeFY11MKAdVgplSM8ue=s96-c\", \"given_name\": \"Malhomme\", \"family_name\": \"Diffusion\", \"locale\": \"fr\", \"iat\": 1675090130, \"exp\": 1675093730}"
    }
},
{
    "model": "admin.logentry",
    "pk": 1,
    "fields": {
        "action_time": "2023-01-27T15:13:12.912Z",
        "user": [
            "malhomme"
        ],
        "content_type": [
            "auth",
            "user"
        ],
        "object_id": "1",
        "object_repr": "malhomme",
        "action_flag": 2,
        "change_message": "[{\"changed\": {\"fields\": [\"First name\", \"Last name\"]}}]"
    }
},
{
    "model": "admin.logentry",
    "pk": 2,
    "fields": {
        "action_time": "2023-01-27T15:31:29.092Z",
        "user": [
            "malhomme"
        ],
        "content_type": [
            "pages",
            "team"
        ],
        "object_id": "1",
        "object_repr": "Dorian",
        "action_flag": 1,
        "change_message": "[{\"added\": {}}]"
    }
},
{
    "model": "admin.logentry",
    "pk": 3,
    "fields": {
        "action_time": "2023-01-27T15:54:54.520Z",
        "user": [
            "malhomme"
        ],
        "content_type": [
            "pages",
            "team"
        ],
        "object_id": "1",
        "object_repr": "Dorian",
        "action_flag": 2,
        "change_message": "[{\"changed\": {\"fields\": [\"Photo\"]}}]"
    }
},
{
    "model": "admin.logentry",
    "pk": 4,
    "fields": {
        "action_time": "2023-01-27T15:55:10.665Z",
        "user": [
            "malhomme"
        ],
        "content_type": [
            "pages",
            "team"
        ],
        "object_id": "1",
        "object_repr": "Dorian",
        "action_flag": 2,
        "change_message": "[{\"changed\": {\"fields\": [\"Photo\"]}}]"
    }
},
{
    "model": "admin.logentry",
    "pk": 5,
    "fields": {
        "action_time": "2023-01-27T15:55:31.960Z",
        "user": [
            "malhomme"
        ],
        "content_type": [
            "pages",
            "team"
        ],
        "object_id": "1",
        "object_repr": "Dorian",
        "action_flag": 2,
        "change_message": "[{\"changed\": {\"fields\": [\"Photo\"]}}]"
    }
},
{
    "model": "admin.logentry",
    "pk": 6,
    "fields": {
        "action_time": "2023-01-27T15:56:49.098Z",
        "user": [
            "malhomme"
        ],
        "content_type": [
            "pages",
            "team"
        ],
        "object_id": "1",
        "object_repr": "Dorian",
        "action_flag": 3,
        "change_message": ""
    }
},
{
    "model": "admin.logentry",
    "pk": 7,
    "fields": {
        "action_time": "2023-01-27T15:59:12.682Z",
        "user": [
            "malhomme"
        ],
        "content_type": [
            "pages",
            "team"
        ],
        "object_id": "2",
        "object_repr": "Michel",
        "action_flag": 1,
        "change_message": "[{\"added\": {}}]"
    }
},
{
    "model": "admin.logentry",
    "pk": 8,
    "fields": {
        "action_time": "2023-01-27T15:59:57.661Z",
        "user": [
            "malhomme"
        ],
        "content_type": [
            "pages",
            "team"
        ],
        "object_id": "3",
        "object_repr": "Stone",
        "action_flag": 1,
        "change_message": "[{\"added\": {}}]"
    }
},
{
    "model": "admin.logentry",
    "pk": 9,
    "fields": {
        "action_time": "2023-01-27T16:00:35.991Z",
        "user": [
            "malhomme"
        ],
        "content_type": [
            "pages",
            "team"
        ],
        "object_id": "4",
        "object_repr": "Michelle",
        "action_flag": 1,
        "change_message": "[{\"added\": {}}]"
    }
},
{
    "model": "admin.logentry",
    "pk": 10,
    "fields": {
        "action_time": "2023-01-27T16:01:01.826Z",
        "user": [
            "malhomme"
        ],
        "content_type": [
            "pages",
            "team"
        ],
        "object_id": "5",
        "object_repr": "Brandon",
        "action_flag": 1,
        "change_message": "[{\"added\": {}}]"
    }
},
{
    "model": "admin.logentry",
    "pk": 11,
    "fields": {
        "action_time": "2023-01-27T20:26:00.249Z",
        "user": [
            "malhomme"
        ],
        "content_type": [
            "cars",
            "car"
        ],
        "object_id": "1",
        "object_repr": "2017 Ferrari 488 GTB",
        "action_flag": 1,
        "change_message": "[{\"added\": {}}]"
    }
},
{
    "model": "admin.logentry",
    "pk": 12,
    "fields": {
        "action_time": "2023-01-28T08:20:32.982Z",
        "user": [
            "malhomme"
        ],
        "content_type": [
            "cars",
            "car"
        ],
        "object_id": "1",
        "object_repr": "2017 Ferrari 488 GTB",
        "action_flag": 2,
        "change_message": "[{\"changed\": {\"fields\": [\"State\", \"City\", \"Color\", \"Year\", \"Condition\", \"Price\", \"Body style\", \"Engine\", \"Transmission\", \"Interior\", \"Miles\", \"Doors\", \"Vin no\", \"Milage\", \"Fuel type\", \"No of owners\", \"Created date\"]}}]"
    }
},
{
    "model": "admin.logentry",
    "pk": 13,
    "fields": {
        "action_time": "2023-01-28T08:25:11.434Z",
        "user": [
            "malhomme"
        ],
        "content_type": [
            "cars",
            "car"
        ],
        "object_id": "2",
        "object_repr": "2017 Ford Edge",
        "action_flag": 1,
        "change_message": "[{\"added\": {}}]"
    }
},
{
    "model": "admin.logentry",
    "pk": 14,
    "fields": {
        "action_time": "2023-01-28T08:29:04.457Z",
        "user": [
            "malhomme"
        ],
        "content_type": [
            "cars",
            "car"
        ],
        "object_id": "3",
        "object_repr": "2017 Ford F-250 Super Duty",
        "action_flag": 1,
        "change_message": "[{\"added\": {}}]"
    }
},
{
    "model": "admin.logentry",
    "pk": 15,
    "fields": {
        "action_time": "2023-01-28T08:32:26.810Z",
        "user": [
            "malhomme"
        ],
        "content_type": [
            "cars",
            "car"
        ],
        "object_id": "4",
        "object_repr": "2017 Jaguar F-PACE",
        "action_flag": 1,
        "change_message": "[{\"added\": {}}]"
    }
},
{
    "model": "admin.logentry",
    "pk": 16,
    "fields": {
        "action_time": "2023-01-28T08:37:07.805Z",
        "user": [
            "malhomme"
        ],
        "content_type": [
            "cars",
            "car"
        ],
        "object_id": "5",
        "object_repr": "2018 Toyota 4Runner",
        "action_flag": 1,
        "change_message": "[{\"added\": {}}]"
    }
},
{
    "model": "admin.logentry",
    "pk": 17,
    "fields": {
        "action_time": "2023-01-28T08:39:26.279Z",
        "user": [
            "malhomme"
        ],
        "content_type": [
            "cars",
            "car"
        ],
        "object_id": "6",
        "object_repr": "2018 Toyota Corolla",
        "action_flag": 1,
        "change_message": "[{\"added\": {}}]"
    }
},
{
    "model": "admin.logentry",
    "pk": 18,
    "fields": {
        "action_time": "2023-01-28T15:59:50.856Z",
        "user": [
            "malhomme"
        ],
        "content_type": [
            "cars",
            "car"
        ],
        "object_id": "6",
        "object_repr": "2018 Toyota Corolla",
        "action_flag": 2,
        "change_message": "[{\"changed\": {\"fields\": [\"Transmission\"]}}]"
    }
},
{
    "model": "admin.logentry",
    "pk": 19,
    "fields": {
        "action_time": "2023-01-30T14:14:16.636Z",
        "user": [
            "malhomme"
        ],
        "content_type": [
            "socialaccount",
            "socialapp"
        ],
        "object_id": "1",
        "object_repr": "Facebook Login",
        "action_flag": 1,
        "change_message": "[{\"added\": {}}]"
    }
},
{
    "model": "admin.logentry",
    "pk": 20,
    "fields": {
        "action_time": "2023-01-30T14:15:33.145Z",
        "user": [
            "malhomme"
        ],
        "content_type": [
            "sites",
            "site"
        ],
        "object_id": "1",
        "object_repr": "localhost:8000",
        "action_flag": 2,
        "change_message": "[{\"changed\": {\"fields\": [\"Domain name\", \"Display name\"]}}]"
    }
},
{
    "model": "admin.logentry",
    "pk": 21,
    "fields": {
        "action_time": "2023-01-30T14:42:23.473Z",
        "user": [
            "malhomme"
        ],
        "content_type": [
            "socialaccount",
            "socialapp"
        ],
        "object_id": "2",
        "object_repr": "Google Login",
        "action_flag": 1,
        "change_message": "[{\"added\": {}}]"
    }
},
{
    "model": "admin.logentry",
    "pk": 22,
    "fields": {
        "action_time": "2023-01-30T16:22:31.654Z",
        "user": [
            "malhomme"
        ],
        "content_type": [
            "auth",
            "user"
        ],
        "object_id": "3",
        "object_repr": "dorian",
        "action_flag": 3,
        "change_message": ""
    }
},
{
    "model": "admin.logentry",
    "pk": 23,
    "fields": {
        "action_time": "2023-01-30T16:22:40.375Z",
        "user": [
            "malhomme"
        ],
        "content_type": [
            "auth",
            "user"
        ],
        "object_id": "1",
        "object_repr": "malhomme",
        "action_flag": 2,
        "change_message": "[{\"changed\": {\"fields\": [\"Email address\"]}}]"
    }
}
]
